{
  "objectInfo" : {
    "schemaVersion" : null,
    "idmcRelease" : null,
    "productRelease" : null,
    "id" : "3sYTO4hivTcgS8f7FtdtAZ",
    "name" : "Process_setup",
    "type" : "PROCESS",
    "metadata" : {
      "modelVersion" : {
        "major" : 1,
        "minor" : 0
      },
      "repoInfo" : {
        "repoHandle" : "taaa-gt-351954-2026-07-13T03:32:53.316Z::pd.xml"
      },
      "contextAttributes" : null,
      "additionalInfo" : {
        "description" : null,
        "contentType" : "application/json; charset=utf-8",
        "documentState" : "VALID"
      }
    }
  },
  "dataFileExtension" : "xml",
  "updateTime" : "2026-07-13T03:38:40.171Z",
  "objectRefs" : [ ],
  "readableFileExtension" : null,
  "readableFilePresent" : false
}