{
  "documentData" : {
    "metadata" : {
      "id" : "c5be40d2-c362-4ac1-8ee8-3be8b6f76750",
      "type" : "REST_API",
      "name" : "REST_API_23(v1)",
      "description" : "this is the second commit i am making by editing api design and creating a new policy standalone",
      "apiName" : "REST_API_23",
      "version" : "v1",
      "status" : "DRAFT",
      "visibility" : "EXTERNAL",
      "revisionNumber" : 1,
      "frsDocumentId" : "fI1zbLcHs2mjYH1tBU9TMj",
      "lastModifiedDate" : 1783882669605,
      "apiClusterId" : "6bd30ab4-7445-4fe6-a7f5-bff8aaf58684",
      "isFixed" : true
    },
    "location" : "1kG78rsULWocyGcMGebvgf",
    "definition" : {
      "id" : "api_definition_1783882669292",
      "operations" : [ {
        "id" : "8b617ad3-9f4f-4d95-b778-d5b8065e944e",
        "title" : "op",
        "description" : "",
        "tags" : [ ],
        "implementationConfigurations" : [ {
          "frsId" : "agvctyI7K83lXgKkH2rT0U",
          "provider" : "CAI_PROCESS",
          "assetName" : "operation_process",
          "description" : "",
          "implementationEndpoint" : "https://pod1-cai.rel.infaqa.com/active-bpel/public/rt/2JW13HLO0EAhUvTbmJWNag/operation_process",
          "inputTransformations" : [ ],
          "outputTransformations" : [ ],
          "responseCodeMappings" : [ ]
        } ],
        "policies" : [ {
          "policy" : {
            "type" : "RATE_LIMITING_POLICY",
            "definition" : {
              "data" : { }
            },
            "inline" : false,
            "inherited" : false,
            "properties" : [ ]
          },
          "selectionType" : "NONE"
        }, {
          "policy" : {
            "type" : "RESPONSE_CACHING_POLICY",
            "definition" : {
              "data" : { }
            },
            "inline" : false,
            "inherited" : false,
            "properties" : [ ]
          },
          "selectionType" : "NONE",
          "notes" : ""
        } ],
        "operationalConfiguration" : { },
        "requestMethod" : "POST",
        "path" : "/operation",
        "pathParameters" : [ ],
        "queryParameters" : [ ],
        "request" : {
          "headers" : [ ],
          "mediaTypes" : [ "APPLICATION_JSON" ],
          "constraints" : {
            "required" : false
          }
        },
        "duplicateOperation" : false,
        "conflict" : false,
        "responses" : [ {
          "headers" : [ ],
          "mediaTypes" : [ "APPLICATION_JSON" ],
          "body" : {
            "metadata" : { },
            "definition" : {
              "fields" : [ ]
            },
            "inline" : false,
            "properties" : [ ]
          },
          "status" : "STATUS_200_OK",
          "description" : "OK."
        } ],
        "ifSkip" : false,
        "issuesParsing" : [ ]
      } ],
      "implementationProviderIds" : [ "agvctyI7K83lXgKkH2rT0U" ]
    },
    "metadata.type" : "REST_API",
    "artifacts" : [ ],
    "groups" : [ ],
    "policies" : [ {
      "policy" : {
        "type" : "AUTHENTICATION_POLICY",
        "metadata" : {
          "id" : "9e72bd90-9d42-43d8-abe6-301fa3687158",
          "name" : "check_auth",
          "description" : "",
          "category" : "SECURITY",
          "type" : "AUTHENTICATION_POLICY",
          "status" : "ENABLED",
          "apiDesignRefCount" : 0,
          "frsDocumentId" : "1bB7zL1JjK7dn1YSalPiMb",
          "frsLocation" : "1kG78rsULWocyGcMGebvgf",
          "frsName" : "check_auth",
          "orgLevelRateLimitPolicy" : false
        },
        "definition" : {
          "data" : { },
          "id" : "3dc74ea3-4c12-4d08-8fec-702b9f5bd3fd",
          "authenticationSchemes" : [ "BASIC", "OAUTH_2" ]
        },
        "inline" : false,
        "inherited" : false,
        "properties" : [ ]
      },
      "selectionType" : "NAMED",
      "notes" : ""
    }, {
      "policy" : {
        "type" : "PII_POLICY",
        "metadata" : {
          "category" : "PRIVACY",
          "type" : "PII_POLICY",
          "apiDesignRefCount" : 0,
          "orgLevelRateLimitPolicy" : false
        },
        "definition" : {
          "data" : { },
          "fields" : [ ]
        },
        "inline" : false,
        "inherited" : false,
        "properties" : [ ]
      },
      "selectionType" : "NONE",
      "notes" : ""
    }, {
      "policy" : {
        "type" : "RATE_LIMITING_POLICY",
        "metadata" : {
          "category" : "OPERATIONAL",
          "type" : "RATE_LIMITING_POLICY",
          "apiDesignRefCount" : 0,
          "orgLevelRateLimitPolicy" : false
        },
        "definition" : {
          "data" : { }
        },
        "inline" : false,
        "inherited" : false,
        "properties" : [ ]
      },
      "selectionType" : "NONE",
      "notes" : ""
    } ],
    "tags" : [ ],
    "properties" : [ {
      "id" : "2ec012a9-6372-4730-aafa-9e1bdff12f42",
      "name" : "ApiImplementationProviderType",
      "value" : "CAI_PROCESS"
    } ]
  },
  "metadata" : {
    "VERSION" : "1.0"
  }
}